{
    "format_version": "1.10.0",
    "animation_controllers": {
        "controller.animation.e7": {
            "states": {
                "default": {
                    "transitions": [
                        {
                            "walking": "(1.0)"
                        }
                    ],
          "on_entry": [
	  "/event entity @s despawning"
          ]
                },
                "walking": {
                    "transitions": [
                        {
                            "default": "(1.0)"
                        }
                    ],
          "on_entry": [
						"/particle minecraft:huge_explosion_emitter ~~~",
						"/playsound random.explode @p",
						"/execute at @s run summon blaze ~~5~",
						"/execute at @s run summon bogged ~~5~",
						"/execute at @s run summon breeze ~~5~",
						"/execute at @s run summon cave_spider ~~5~",
						"/execute at @s run summon creeper ~~5~",
						"/execute at @s run summon drowned ~~5~",
						"/execute at @s run summon elder_guardian ~~5~",
						"/execute at @s run summon endermite ~~5~",
						"/execute at @s run summon evoker ~~5~",
						"/execute at @s run summon hoglin ~~5~",
						"/execute at @s run summon husk ~~5~",
						"/execute at @s run summon illusioner ~~5~",
						"/execute at @s run summon phantom ~~5~",
						"/execute at @s run summon piglin ~~5~",
						"/execute at @s run summon piglin_brute ~~5~",
						"/execute at @s run summon pillager ~~5~",
						"/execute at @s run summon ravager ~~5~",
						"/execute at @s run summon shulker ~~5~",
						"/execute at @s run summon skeleton ~~5~",
						"/execute at @s run summon slime ~~5~",
						"/execute at @s run summon spider ~~5~",
						"/execute at @s run summon vex ~~5~",
						"/execute at @s run summon warden ~~5~",
						"/execute at @s run summon zombie_villager ~~5~",
						"/execute at @s run summon zombiefied_piglin ~~5~",
						"/execute at @s run summon allay ~~5~",
						"/execute at @s run summon armadillo ~~5~",
						"/execute at @s run summon axolotl ~~5~",
						"/execute at @s run summon bat ~~5~",
						"/execute at @s run summon bee ~~5~",
						"/execute at @s run summon camel ~~5~",
						"/execute at @s run summon cat ~~5~",
						"/execute at @s run summon chicken ~~5~",
						"/execute at @s run summon cod ~~5~",
						"/execute at @s run summon cow ~~5~",
						"/execute at @s run summon dolphin ~~5~",
						"/execute at @s run summon donkey ~~5~",
						"/execute at @s run summon fox ~~5~",
						"/execute at @s run summon frog ~~5~",
						"/execute at @s run summon glow_squid ~~5~",
						"/execute at @s run summon goat ~~5~",
						"/execute at @s run summon horse ~~5~",
						"/execute at @s run summon iron_golem ~~5~",
						"/execute at @s run summon llama ~~5~",
						"/execute at @s run summon mooshroom ~~5~",
						"/execute at @s run summon mule ~~5~",
						"/execute at @s run summon ocelot ~~5~",
						"/execute at @s run summon panda ~~5~",
						"/execute at @s run summon parrot ~~5~",
						"/execute at @s run summon pig ~~5~",
						"/execute at @s run summon polar_bear ~~5~",
						"/execute at @s run summon pufferfish ~~5~",
						"/execute at @s run summon rabbit ~~5~",
						"/execute at @s run summon salmon ~~5~",
						"/execute at @s run summon sheep ~~5~",
						"/execute at @s run summon skeleton_horse ~~5~",
						"/execute at @s run summon sniffer ~~5~",
						"/execute at @s run summon snow_golem ~~5~",
						"/execute at @s run summon squid ~~5~",
						"/execute at @s run summon strider ~~5~",
						"/execute at @s run summon tadpole ~~5~",
						"/execute at @s run summon trader_llama ~~5~",
						"/execute at @s run summon turtle ~~5~",
						"/execute at @s run summon tropical_fish ~~5~",
						"/execute at @s run summon villager ~~5~",
						"/execute at @s run summon wandering_trader ~~5~",
						"/execute at @s run summon wolf ~~5~",
						"/execute at @s run summon zombie_horse ~~5~",
						"/event entity @s despawning"
          ]
                }
            }
        }
    }
}