{
  "format_version": "1.20.60",
  "minecraft:block": {
    "description": {
      "identifier": "zex:tnt15",
      "menu_category": {
        "category": "construction"
      }
    },
    "components": {
      "minecraft:material_instances": {
        "up": {
          "texture": "tnt15_top"
        },
        "down": {
          "texture": "tnt15_bottom"
        },
        "north": {
          "texture": "tnt15_side"
        },
        "south": {
          "texture": "tnt15_side"
        },
        "east": {
          "texture": "tnt15_side"
        },
        "west": {
          "texture": "tnt15_side"
        }
      },
      "minecraft:geometry": "minecraft:geometry.full_block",
      "minecraft:selection_box": {
        "origin": [
          -8,
          0,
          -8
        ],
        "size": [
          16,
          16,
          16
        ]
      },
      "minecraft:custom_components": [
        "zex:ignite"
      ],
      "minecraft:light_emission": 0,
      "minecraft:light_dampening": 15,
      "minecraft:map_color": "#00ff00"
    }
  }
}